lasersafety/__init__.py
lasersafety/__main__.py
lasersafety/classes.py
lasersafety/en207.py
lasersafety/en208.py
lasersafety/laser.py
lasersafety/modes.py
lasersafety/utils.py
lasersafety-0.10.1.dist-info/LICENSE
lasersafety-0.10.1.dist-info/METADATA
lasersafety-0.10.1.dist-info/WHEEL
lasersafety-0.10.1.dist-info/entry_points.txt
lasersafety-0.10.1.dist-info/RECORD
