Metadata-Version: 2.3
Name: lasersafety
Version: 0.10.1
Summary: A package for the computations of EN207 and EN208
License: MIT
Author: Yoann Piétri
Author-email: me@nanoy.fr
Requires-Python: >=3.11
Classifier: Development Status :: 4 - Beta
Classifier: Intended Audience :: Science/Research
Classifier: License :: OSI Approved :: MIT License
Classifier: Natural Language :: English
Classifier: Topic :: Scientific/Engineering :: Physics
Requires-Dist: numpy (>=2.2.4,<3.0.0)
Project-URL: Documentation, https://lasersafety.readthedocs.io/
Project-URL: Repository, https://github.com/nanoy42/lasersafety/
